junity/__init__.py
junity/_version.py
junity/config.py
junity/handlers.py
junity/preview_handler.py
junity/settings_handler.py
junity/utils.py
junity/tests/conftest.py
junity/tests/test_preview_handler.py
junity/tests/test_settings_handlers.py
junity-0.7.8.data/data/etc/jupyter/jupyter_server_config.d/junity.json
junity-0.7.8.data/data/share/jupyter/labextensions/junity/package.json
junity-0.7.8.data/data/share/jupyter/labextensions/junity/schemas/junity/package.json.orig
junity-0.7.8.data/data/share/jupyter/labextensions/junity/schemas/junity/settings.json
junity-0.7.8.data/data/share/jupyter/labextensions/junity/static/162.762fcb69a70bfd8e967c.js
junity-0.7.8.data/data/share/jupyter/labextensions/junity/static/25.c13d675d9a42dabcd546.js
junity-0.7.8.data/data/share/jupyter/labextensions/junity/static/260.e858dc1dab6957a8ada3.js
junity-0.7.8.data/data/share/jupyter/labextensions/junity/static/306.f62435968212b1323d6d.js
junity-0.7.8.data/data/share/jupyter/labextensions/junity/static/352.9993a4bfbf8c6868f038.js
junity-0.7.8.data/data/share/jupyter/labextensions/junity/static/359.9749689c1c173f81fa7a.js
junity-0.7.8.data/data/share/jupyter/labextensions/junity/static/377.c8d493d938175b3a0853.js
junity-0.7.8.data/data/share/jupyter/labextensions/junity/static/41.261bb69e60be000ac0a4.js
junity-0.7.8.data/data/share/jupyter/labextensions/junity/static/41.261bb69e60be000ac0a4.js.LICENSE.txt
junity-0.7.8.data/data/share/jupyter/labextensions/junity/static/456.0accebea78334a507a0a.js
junity-0.7.8.data/data/share/jupyter/labextensions/junity/static/456.0accebea78334a507a0a.js.LICENSE.txt
junity-0.7.8.data/data/share/jupyter/labextensions/junity/static/468.f818db5d3ac8ed6f27d5.js
junity-0.7.8.data/data/share/jupyter/labextensions/junity/static/487.1d40a27d582c0388390d.js
junity-0.7.8.data/data/share/jupyter/labextensions/junity/static/500.06aaf26a53b026b5b2e2.js
junity-0.7.8.data/data/share/jupyter/labextensions/junity/static/56.c75da183a6797a5434ed.js
junity-0.7.8.dist-info/METADATA
junity-0.7.8.dist-info/WHEEL
junity-0.7.8.dist-info/licenses/LICENSE
junity-0.7.8.dist-info/RECORD
