Metadata-Version: 2.3
Name: junity
Version: 0.7.8
Summary: A JupyterLab extension for Unity Catalog
Project-URL: Homepage, https://github.com/dan1elt0m/junity
Project-URL: Bug Tracker, https://github.com/dan1elt0m/junity/issues
Project-URL: Repository, https://github.com/dan1elt0m/junity.git
Author-email: Daniel Tom <d.e.tom89@gmail.com>
License: BSD 3-Clause License
Keywords: jupyter,jupyterlab,jupyterlab-extension
Classifier: Framework :: Jupyter
Classifier: Framework :: Jupyter :: JupyterLab
Classifier: Framework :: Jupyter :: JupyterLab :: 4
Classifier: Framework :: Jupyter :: JupyterLab :: Extensions
Classifier: Framework :: Jupyter :: JupyterLab :: Extensions :: Prebuilt
Classifier: License :: OSI Approved :: BSD License
Classifier: Programming Language :: Python
Classifier: Programming Language :: Python :: 3
Classifier: Programming Language :: Python :: 3.8
Classifier: Programming Language :: Python :: 3.9
Classifier: Programming Language :: Python :: 3.10
Classifier: Programming Language :: Python :: 3.11
Classifier: Programming Language :: Python :: 3.12
Requires-Python: >=3.8
Requires-Dist: duckdb>=1.0
Requires-Dist: pandas>=2.2
Provides-Extra: test
Requires-Dist: coverage; extra == 'test'
Requires-Dist: pytest; extra == 'test'
Requires-Dist: pytest-asyncio; extra == 'test'
Requires-Dist: pytest-cov; extra == 'test'
Requires-Dist: pytest-jupyter[server]>=0.6.0; extra == 'test'
